pytest_selenium/__init__.py
pytest_selenium/drivers/__init__.py
pytest_selenium/drivers/appium.py
pytest_selenium/drivers/browserstack.py
pytest_selenium/drivers/chrome.py
pytest_selenium/drivers/cloud.py
pytest_selenium/drivers/crossbrowsertesting.py
pytest_selenium/drivers/edge.py
pytest_selenium/drivers/firefox.py
pytest_selenium/drivers/internet_explorer.py
pytest_selenium/drivers/remote.py
pytest_selenium/drivers/safari.py
pytest_selenium/drivers/saucelabs.py
pytest_selenium/drivers/testingbot.py
pytest_selenium/exceptions.py
pytest_selenium/hooks.py
pytest_selenium/pytest_selenium.py
pytest_selenium/safety.py
pytest_selenium/utils.py
pytest_selenium-4.0.0.dist-info/entry_points.txt
pytest_selenium-4.0.0.dist-info/LICENSE
pytest_selenium-4.0.0.dist-info/WHEEL
pytest_selenium-4.0.0.dist-info/METADATA
pytest_selenium-4.0.0.dist-info/RECORD
