Metadata-Version: 2.1
Name: pytest-selenium
Version: 4.0.0
Summary: pytest plugin for Selenium
Home-page: https://github.com/pytest-dev/pytest-selenium
License: MPL-2.0
Keywords: pytest,selenium,saucelabs,browserstack,webqa,qa
Author: Dave Hunt
Author-email: dhunt@mozilla.com
Requires-Python: >=3.7,<4.0
Classifier: Development Status :: 5 - Production/Stable
Classifier: Framework :: Pytest
Classifier: Intended Audience :: Developers
Classifier: License :: OSI Approved
Classifier: Operating System :: MacOS :: MacOS X
Classifier: Operating System :: Microsoft :: Windows
Classifier: Operating System :: POSIX
Classifier: Programming Language :: Python :: 3
Classifier: Programming Language :: Python :: 3.7
Classifier: Programming Language :: Python :: 3.8
Classifier: Programming Language :: Python :: 3.9
Classifier: Programming Language :: Python :: 3.10
Classifier: Topic :: Software Development :: Quality Assurance
Classifier: Topic :: Software Development :: Testing
Classifier: Topic :: Utilities
Provides-Extra: appium
Requires-Dist: appium-python-client (>=2.0.0,<3.0.0); extra == "appium"
Requires-Dist: pytest (>=6.0.0,<7.0.0)
Requires-Dist: pytest-base-url (>=2.0.0,<3.0.0)
Requires-Dist: pytest-html (>=2.0.0)
Requires-Dist: pytest-variables (>=2.0.0,<3.0.0)
Requires-Dist: requests (>=2.26.0,<3.0.0)
Requires-Dist: selenium (>=4.0.0,<5.0.0)
Requires-Dist: tenacity (>=6.0.0,<7.0.0)
Project-URL: Repository, https://github.com/pytest-dev/pytest-selenium
